djangosaml2idp/__init__.py
djangosaml2idp/admin.py
djangosaml2idp/error_views.py
djangosaml2idp/forms.py
djangosaml2idp/idp.py
djangosaml2idp/models.py
djangosaml2idp/processors.py
djangosaml2idp/urls.py
djangosaml2idp/utils.py
djangosaml2idp/views.py
djangosaml2idp/migrations/0001_initial.py
djangosaml2idp/migrations/0002_persistent_id.py
djangosaml2idp/migrations/__init__.py
djangosaml2idp/templates/djangosaml2idp/error.html
djangosaml2idp/templates/djangosaml2idp/login.html
djsaml2_idp_app-0.7.4.dist-info/LICENSE.txt
djsaml2_idp_app-0.7.4.dist-info/METADATA
djsaml2_idp_app-0.7.4.dist-info/WHEEL
djsaml2_idp_app-0.7.4.dist-info/top_level.txt
djsaml2_idp_app-0.7.4.dist-info/RECORD
