Metadata-Version: 2.1
Name: djsaml2-idp-app
Version: 0.7.4
Summary: SAML 2.0 Identity Provider for Django
Home-page: https://github.com/abybaddi009/djangosaml2idp/
Author: Abhishek Baddi
Author-email: abybaddi009@gmail.com
Maintainer: Abhishek Baddi
License: Apache Software License 2.0
Keywords: django,pysaml2,sso,saml2,federated authentication,authentication,idp
Classifier: Development Status :: 5 - Production/Stable
Classifier: Environment :: Web Environment
Classifier: Framework :: Django
Classifier: Framework :: Django :: 2.2
Classifier: Framework :: Django :: 3.0
Classifier: Framework :: Django :: 3.1
Classifier: Intended Audience :: Developers
Classifier: Intended Audience :: Information Technology
Classifier: License :: OSI Approved :: Apache Software License
Classifier: Operating System :: OS Independent
Classifier: Programming Language :: Python
Classifier: Programming Language :: Python :: 3
Classifier: Programming Language :: Python :: 3.6
Classifier: Programming Language :: Python :: 3.7
Classifier: Programming Language :: Python :: 3.8
Classifier: Programming Language :: Python :: 3.9
Classifier: Topic :: Internet :: WWW/HTTP
Classifier: Topic :: Internet :: WWW/HTTP :: WSGI
Classifier: Topic :: Security
Classifier: Topic :: Software Development :: Libraries :: Application Frameworks
Classifier: Topic :: Internet :: WWW/HTTP :: Dynamic Content
Classifier: Topic :: Software Development :: Libraries :: Python Modules
Requires-Python: >=3.6
License-File: LICENSE.txt
Requires-Dist: django >=2.2
Requires-Dist: pysaml2 >=6.5.1
Requires-Dist: pytz
Requires-Dist: arrow
Provides-Extra: testing
Requires-Dist: pytest ; extra == 'testing'
Requires-Dist: pytest-runner ; extra == 'testing'
Requires-Dist: pytest-django ; extra == 'testing'
Requires-Dist: pytest-cov ; extra == 'testing'
Requires-Dist: pytest-pythonpath ; extra == 'testing'
Requires-Dist: pytest-mock ; extra == 'testing'
Requires-Dist: requests-mock ; extra == 'testing'
